pybullet_workshop_23/__init__.py
pybullet_workshop_23/envs/__init__.py
pybullet_workshop_23/envs/pybullet_env.py
pybullet_workshop_23-0.3.8.dist-info/METADATA
pybullet_workshop_23-0.3.8.dist-info/WHEEL
pybullet_workshop_23-0.3.8.dist-info/top_level.txt
pybullet_workshop_23-0.3.8.dist-info/RECORD
