Metadata-Version: 2.1
Name: pybullet-workshop-23
Version: 0.3.8
Summary: A OpenAI Gym Env for pybullet and vision
Requires-Dist: gym
